hazenlib/HazenTask.py
hazenlib/__init__.py
hazenlib/_version.py
hazenlib/acr_uniformity.py
hazenlib/exceptions.py
hazenlib/logger.py
hazenlib/relaxometry.py
hazenlib/shapes.py
hazenlib/snr_map.py
hazenlib/tools.py
hazenlib/tasks/__init__.py
hazenlib/tasks/acr_uniformity.py
hazenlib/tasks/ghosting.py
hazenlib/tasks/relaxometry.py
hazenlib/tasks/slice_position.py
hazenlib/tasks/slice_width.py
hazenlib/tasks/snr.py
hazenlib/tasks/snr_map.py
hazenlib/tasks/spatial_resolution.py
hazenlib/tasks/uniformity.py
tests/__init__.py
tests/test_acr_uniformity.py
tests/test_ghosting.py
tests/test_hazenlib.py
tests/test_relaxometry.py
tests/test_slice_position.py
tests/test_slice_width.py
tests/test_snr.py
tests/test_snr_map.py
tests/test_spatial_resolution.py
tests/test_tools.py
tests/test_uniformity.py
test_hazen-1.0.3.dist-info/LICENSE.txt
test_hazen-1.0.3.dist-info/METADATA
test_hazen-1.0.3.dist-info/WHEEL
test_hazen-1.0.3.dist-info/entry_points.txt
test_hazen-1.0.3.dist-info/top_level.txt
test_hazen-1.0.3.dist-info/RECORD
