Metadata-Version: 2.1
Name: test-hazen
Version: 1.0.3
Summary: An automatic MRI QA tool
Home-page: https://bitbucket.org/gsttmri/hazen
Author: Shuaib, Haris
Author-email: mohammad_haris.shuaib@kcl.ac.uk
Classifier: Development Status :: 2 - Pre-Alpha
Classifier: Programming Language :: Python
Classifier: Programming Language :: Python :: 3
Classifier: Programming Language :: Python :: 3.9
License-File: LICENSE.txt
Requires-Dist: pydicom (==2.2.2)
Requires-Dist: numpy (==1.21.4)
Requires-Dist: matplotlib (==3.5.1)
Requires-Dist: docopt (==0.6.2)
Requires-Dist: opencv-python-headless (==4.6.0.66)
Requires-Dist: scikit-image (==0.19.2)
Requires-Dist: scipy (==1.8.0)
Requires-Dist: imutils (==0.5.3)
Requires-Dist: colorlog (==6.6.0)
